corp_error_agent.pth
corp_error_agent/__init__.py
corp_error_agent/cli.py
corp_error_agent/sitecustomize.py
corp_error_agent-0.4.2.dist-info/METADATA
corp_error_agent-0.4.2.dist-info/WHEEL
corp_error_agent-0.4.2.dist-info/entry_points.txt
corp_error_agent-0.4.2.dist-info/top_level.txt
corp_error_agent-0.4.2.dist-info/RECORD
