Metadata-Version: 2.4
Name: corp_error_agent
Version: 0.4.2
Summary: Runtime agent that captures uncaught errors + env snapshot and prints data‑driven CLI hints.
Home-page: https://github.com/arielfayol37/corp_error_agent
Author: Fayol Ateufack
Author-email: Fayol Ateufack <arielfayol1@gmail.com>
License: MIT
Project-URL: Source, https://github.com/arielfayol37/corp_error_agent
Classifier: Programming Language :: Python :: 3
Classifier: Operating System :: OS Independent
Requires-Python: >=3.8
Requires-Dist: requests>=2.31
Requires-Dist: platformdirs>=3.10
Dynamic: author
Dynamic: home-page
Dynamic: requires-python
